{
    "curriculum": {
        "Grade1": {
            "Term1": {
                "Mandatory": [
                    "공통국어1",
                    "공통수학1",
                    "공통영어1",
                    "한국사1",
                    "통합사회1",
                    "통합과학1",
                    "과학탐구실험1",
                    "체육1",
                    "음악"
                ],
                "Select": [
                    "화학",
                    "로봇과 공학세계"
                ]
            },
            "Term2": {
                "Mandatory": [
                    "공통국어2",
                    "공통수학2",
                    "공통영어2",
                    "한국사2",
                    "통합사회2",
                    "통합과학2",
                    "과학탐구실험2",
                    "체육2",
                    "음악 감상과 비평"
                ],
                "Select": [
                    "화학",
                    "로봇과 공학세계"
                ]
            }
        },
        "Grade2": {
            "Term1": {
                "Mandatory": [
                    "문학",
                    "대수",
                    "영어Ⅰ",
                    "확률과 통계",
                    "운동과 건강"
                ],
                "Select_Core": [
                    "세계사",
                    "세계시민과 지리",
                    "법과 사회",
                    "윤리와 사상",
                    "물리학",
                    "생명과학",
                    "지구과학",
                    "인공지능 기초"
                ],
                "Select_Language": [
                    "중국어",
                    "일본어"
                ]
            },
            "Term2": {
                "Mandatory": [
                    "독서와 작문",
                    "미적분Ⅰ",
                    "영어Ⅱ",
                    "스포츠 생활1"
                ],
                "Select_Basic": [
                    "매체 의사소통",
                    "기하",
                    "영어 발표와 토론"
                ],
                "Select_Core": [
                    "현대사회와 윤리",
                    "경제",
                    "동아시아 역사 기행",
                    "한국지리 탐구",
                    "역학과 에너지",
                    "물질과 에너지",
                    "세포와 물질대사",
                    "지구시스템과학",
                    "창의 공학 설계"
                ],
                "Select_Language": [
                    "중국어 회화",
                    "일본어 회화"
                ],
                "Select_General": [
                    "교육의 이해",
                    "인간과 경제활동",
                    "진로와 직업",
                    "보건",
                    "인간과 심리",
                    "논술"
                ]
            }
        },
        "Grade3": {
            "Term1": {
                "Mandatory": [
                    "화법과 언어",
                    "스포츠 과학",
                    "미술 감상과 비평"
                ],
                "Select_Track": [
                    "주제 탐구 독서",
                    "경제 수학",
                    "미적분Ⅱ",
                    "영미 문학 읽기",
                    "심화 영어 독해와 작문"
                ],
                "Select_Advanced": [
                    "사회와 문화",
                    "도시의 미래 탐구",
                    "기후변화와 지속가능한 세계",
                    "역사로 탐구하는 현대 세계",
                    "전자기와 양자",
                    "화학 반응의 세계",
                    "생물의 유전",
                    "행성우주과학",
                    "화학 실험"
                ]
            },
            "Term2": {
                "Mandatory": [
                    "심화 영어",
                    "스포츠 생활2",
                    "미술 창작"
                ],
                "Select_Track": [
                    "독서 토론과 글쓰기",
                    "언어생활 탐구",
                    "수학과제 탐구",
                    "실용 통계",
                    "미디어 영어",
                    "실생활 영어 회화"
                ],
                "Select_Advanced": [
                    "기후변화와 환경생태",
                    "금융과 경제생활",
                    "여행지리",
                    "윤리문제 탐구",
                    "과학의 역사와 문화",
                    "융합과학 탐구"
                ],
                "Select_General": [
                    "진로와 직업",
                    "보건",
                    "인간과 심리",
                    "논술",
                    "중국 문화",
                    "일본 문화",
                    "생태와 환경",
                    "논리와 사고"
                ]
            }
        }
    }
}